dl4cv_oda/__init__.py
dl4cv_oda/cleanup.py
dl4cv_oda/cli.py
dl4cv_oda/tiling.py
dl4cv_oda/train.py
dl4cv_oda/yolo_converter.py
dl4cv_oda-0.1.3.dist-info/METADATA
dl4cv_oda-0.1.3.dist-info/WHEEL
dl4cv_oda-0.1.3.dist-info/entry_points.txt
dl4cv_oda-0.1.3.dist-info/RECORD
