Metadata-Version: 2.4
Name: dl4cv-oda
Version: 0.1.3
Summary: Coconut tree detection from drone imagery
Author: krschap
License: MIT
Keywords: aerial-imagery,object-detection,remote-sensing,yolo
Classifier: Development Status :: 3 - Alpha
Classifier: Intended Audience :: Science/Research
Classifier: License :: OSI Approved :: MIT License
Classifier: Programming Language :: Python :: 3
Classifier: Programming Language :: Python :: 3.11
Classifier: Programming Language :: Python :: 3.12
Classifier: Programming Language :: Python :: 3.13
Requires-Python: >=3.11
Requires-Dist: geomltoolkits>=0.4.2
Requires-Dist: geopandas>=1.1.2
Requires-Dist: pandas>=2.0.0
Requires-Dist: pillow>=10.0.0
Requires-Dist: pyyaml>=6.0.3
Requires-Dist: rasterio>=1.3.0
Requires-Dist: rich>=13.0.0
Requires-Dist: shapely>=2.1.2
Requires-Dist: typer>=0.12.0
Requires-Dist: ultralytics>=8.3.250
Provides-Extra: dev
Requires-Dist: commitizen>=3.0.0; extra == 'dev'
Requires-Dist: ipykernel>=7.1.0; extra == 'dev'
Requires-Dist: jupyter>=1.0.0; extra == 'dev'
Requires-Dist: pytest>=8.0.0; extra == 'dev'
Requires-Dist: ruff>=0.3.0; extra == 'dev'
